[
    {"text": "fasttravel.tumbleweed", "x": -109.3203,"y": 26.8594},
    {"text": "fasttravel.armadillo", "x": -104.3750,"y": 53.4141},
    {"text": "fasttravel.macfarlanes", "x": -101.5156,"y": 72.4141},
    {"text": "fasttravel.manzanita", "x": -88.5859,"y": 80.7891},
    {"text": "fasttravel.blackwater", "x": -82.9141,"y": 99.7656},
    {"text": "fasttravel.strawberry", "x": -70.0313,"y": 84.2969},
    {"text": "fasttravel.valentine", "x": -53.5781,"y": 108.3828},
    {"text": "fasttravel.colter", "x": -25.9297,"y": 91.0469},
    {"text": "fasttravel.emerald", "x": -56.7734,"y": 134.8203},
    {"text": "fasttravel.rhodes", "x": -83.6641,"y": 130.6563},
    {"text": "fasttravel.wapiti", "x": -29.7266,"y": 118.7891},
    {"text": "fasttravel.van_horn", "x": -53.7031,"y": 156.3203},
    {"text": "fasttravel.annesburg", "x": -43.4688,"y": 156.7656},
    {"text": "fasttravel.saint_denis", "x": -86.3281,"y": 152.6797},
    {"text": "fasttravel.lagras", "x": -72.5938,"y": 143.8594}
]